jupyterlab_plugin_graph/__init__.py
jupyterlab_plugin_graph/_version.py
jupyterlab_plugin_graph/labextension/package.json
jupyterlab_plugin_graph/labextension/static/549.bba33d6813820133a3b7.js
jupyterlab_plugin_graph/labextension/static/58.4656fa0c7f02f2cf8532.js
jupyterlab_plugin_graph/labextension/static/58.4656fa0c7f02f2cf8532.js.LICENSE.txt
jupyterlab_plugin_graph/labextension/static/651.d8fa1df3cc80c09388a0.js
jupyterlab_plugin_graph/labextension/static/remoteEntry.a5b4d5aa1e64f3e5b76c.js
jupyterlab_plugin_graph/labextension/static/style.js
jupyterlab_plugin_graph/labextension/static/third-party-licenses.json
jupyterlab_plugin_graph-0.2.1.data/data/share/jupyter/labextensions/jupyterlab-plugin-graph/install.json
jupyterlab_plugin_graph-0.2.1.data/data/share/jupyter/labextensions/jupyterlab-plugin-graph/package.json
jupyterlab_plugin_graph-0.2.1.data/data/share/jupyter/labextensions/jupyterlab-plugin-graph/static/549.bba33d6813820133a3b7.js
jupyterlab_plugin_graph-0.2.1.data/data/share/jupyter/labextensions/jupyterlab-plugin-graph/static/58.4656fa0c7f02f2cf8532.js
jupyterlab_plugin_graph-0.2.1.data/data/share/jupyter/labextensions/jupyterlab-plugin-graph/static/58.4656fa0c7f02f2cf8532.js.LICENSE.txt
jupyterlab_plugin_graph-0.2.1.data/data/share/jupyter/labextensions/jupyterlab-plugin-graph/static/651.d8fa1df3cc80c09388a0.js
jupyterlab_plugin_graph-0.2.1.data/data/share/jupyter/labextensions/jupyterlab-plugin-graph/static/remoteEntry.a5b4d5aa1e64f3e5b76c.js
jupyterlab_plugin_graph-0.2.1.data/data/share/jupyter/labextensions/jupyterlab-plugin-graph/static/style.js
jupyterlab_plugin_graph-0.2.1.data/data/share/jupyter/labextensions/jupyterlab-plugin-graph/static/third-party-licenses.json
jupyterlab_plugin_graph-0.2.1.dist-info/LICENSE
jupyterlab_plugin_graph-0.2.1.dist-info/METADATA
jupyterlab_plugin_graph-0.2.1.dist-info/WHEEL
jupyterlab_plugin_graph-0.2.1.dist-info/top_level.txt
jupyterlab_plugin_graph-0.2.1.dist-info/RECORD
